contextor/__init__.py
contextor/__main__.py
contextor/cli.py
contextor/clipboard.py
contextor/main.py
contextor/selection.py
contextor/tree.py
contextor/utils.py
contextor/signatures/__init__.py
contextor/signatures/javascript.py
contextor/signatures/markdown.py
contextor/signatures/processor.py
contextor/signatures/python.py
contextor/signatures/sql.py
contextor-1.4.5.dist-info/METADATA
contextor-1.4.5.dist-info/WHEEL
contextor-1.4.5.dist-info/entry_points.txt
contextor-1.4.5.dist-info/licenses/LICENSE
contextor-1.4.5.dist-info/RECORD
