Metadata-Version: 2.4
Name: contextor
Version: 1.4.5
Summary: Create context files from your codebase for AI conversations
Author-email: Salih Ergüt <salih.ergut@gmail.com>
License-File: LICENSE
Classifier: Development Status :: 3 - Alpha
Classifier: Intended Audience :: Developers
Classifier: License :: OSI Approved :: MIT License
Classifier: Programming Language :: Python :: 3
Requires-Python: >=3.9
Requires-Dist: pathspec>=0.12.1
Requires-Dist: pyperclip>=1.8.2
Requires-Dist: questionary>=1.10.0
Requires-Dist: tomli>=2.0.1
Provides-Extra: test
Requires-Dist: pytest-cov>=4.0; extra == 'test'
Requires-Dist: pytest>=7.0; extra == 'test'
